flask-sqlalchemy-stubs/__init__.pyi
flask-sqlalchemy-stubs/_compat.pyi
flask-sqlalchemy-stubs/model.pyi
flask-sqlalchemy-stubs/utils.pyi
flask_sqlalchemy-stubs/__init__.pyi
flask_sqlalchemy-stubs/_compat.pyi
flask_sqlalchemy-stubs/model.pyi
flask_sqlalchemy-stubs/utils.pyi
voluptuous-stubs/__init__.pyi
voluptuous-stubs/error.pyi
voluptuous-stubs/humanize.pyi
voluptuous-stubs/schema_builder.pyi
voluptuous-stubs/util.pyi
voluptuous-stubs/validators.pyi
flask_sqlalchemy_stubs-0.2.dist-info/METADATA
flask_sqlalchemy_stubs-0.2.dist-info/WHEEL
flask_sqlalchemy_stubs-0.2.dist-info/top_level.txt
flask_sqlalchemy_stubs-0.2.dist-info/RECORD
