Metadata-Version: 2.1
Name: flask_sqlalchemy-stubs
Version: 0.2
Summary: flask_sqlalchemy stubs
Home-page: https://github.com/ryanwang520/flask_sqlalchemy-stubs
Author: Ryan Wang
Author-email: hwwangwang@gmail.com
License: MIT License
Platform: UNKNOWN
Classifier: Development Status :: 3 - Alpha
Classifier: Programming Language :: Python :: 3
